[
  {
    "key": "INITIALKEY123",
    "ip": null
  },
  {
    "key": "53F8F2ED2CC3F879",
    "ip": null
  },
  {
    "key": "1C63ABD5B8B384E7",
    "ip": null
  },
  {
    "key": "74EE7880CEA64B32",
    "ip": null
  },
  {
    "key": "84BA2D40FF45E8B6",
    "ip": null
  },
  {
    "key": "86187E8662A27A1C",
    "ip": null
  },
  {
    "key": "FA9DE413120BE898",
    "ip": null
  },
  {
    "key": "F698E6BC34FFE13B",
    "ip": null
  },
  {
    "key": "8DFD5CB58095837C",
    "ip": null
  },
  {
    "key": "889C713D23D25D7D",
    "ip": null
  },
  {
    "key": "6D33E4964F8CA99F",
    "ip": null
  }
]